jiter/__init__.py
jiter/jiter.py
jiter_pupy-0.8.5.dist-info/METADATA
jiter_pupy-0.8.5.dist-info/WHEEL
jiter_pupy-0.8.5.dist-info/licenses/LICENSE
jiter_pupy-0.8.5.dist-info/RECORD
